<?xml version="1.0" encoding="UTF-8"?>

    <dict>
        <key>frames</key>
        <dict>
            <key>057_14Tower.png</key>
            <dict>
                <key>frame</key>
                <string>{{1,1},{90,156}}</string>
                <key>offset</key>
                <string>{0,0}</string>
                <key>rotated</key>
                <false/>
                <key>sourceColorRect</key>
                <string>{{0,0},{90,156}}</string>
                <key>sourceSize</key>
                <string>{90,156}</string>
            </dict>
            <key>058_16FrontNew.png</key>
            <dict>
                <key>frame</key>
                <string>{{91,1},{510,38}}</string>
                <key>offset</key>
                <string>{0,0}</string>
                <key>rotated</key>
                <false/>
                <key>sourceColorRect</key>
                <string>{{0,0},{510,38}}</string>
                <key>sourceSize</key>
                <string>{510,38}</string>
            </dict>
            <key>059_17FrontNew.png</key>
            <dict>
                <key>frame</key>
                <string>{{1,157},{510,34}}</string>
                <key>offset</key>
                <string>{0,0}</string>
                <key>rotated</key>
                <false/>
                <key>sourceColorRect</key>
                <string>{{0,0},{510,34}}</string>
                <key>sourceSize</key>
                <string>{510,34}</string>
            </dict>
            <key>060_18FrontNew.png</key>
            <dict>
                <key>frame</key>
                <string>{{511,157},{510,47}}</string>
                <key>offset</key>
                <string>{0,0}</string>
                <key>rotated</key>
                <false/>
                <key>sourceColorRect</key>
                <string>{{0,0},{510,47}}</string>
                <key>sourceSize</key>
                <string>{510,47}</string>
            </dict>
            <key>061_19FrontNew.png</key>
            <dict>
                <key>frame</key>
                <string>{{1,204},{510,60}}</string>
                <key>offset</key>
                <string>{0,0}</string>
                <key>rotated</key>
                <false/>
                <key>sourceColorRect</key>
                <string>{{0,0},{510,60}}</string>
                <key>sourceSize</key>
                <string>{510,60}</string>
            </dict>
            <key>062_20FrontNew.png</key>
            <dict>
                <key>frame</key>
                <string>{{511,204},{510,58}}</string>
                <key>offset</key>
                <string>{0,0}</string>
                <key>rotated</key>
                <false/>
                <key>sourceColorRect</key>
                <string>{{0,0},{510,58}}</string>
                <key>sourceSize</key>
                <string>{510,58}</string>
            </dict>
            <key>063_13BackNew.png</key>
            <dict>
                <key>frame</key>
                <string>{{1,264},{510,214}}</string>
                <key>offset</key>
                <string>{0,0}</string>
                <key>rotated</key>
                <false/>
                <key>sourceColorRect</key>
                <string>{{0,0},{510,214}}</string>
                <key>sourceSize</key>
                <string>{510,214}</string>
            </dict>
            <key>064_14BackNew.png</key>
            <dict>
                <key>frame</key>
                <string>{{511,264},{510,258}}</string>
                <key>offset</key>
                <string>{0,0}</string>
                <key>rotated</key>
                <false/>
                <key>sourceColorRect</key>
                <string>{{0,0},{510,258}}</string>
                <key>sourceSize</key>
                <string>{510,258}</string>
            </dict>
            <key>065_15BackNew.png</key>
            <dict>
                <key>frame</key>
                <string>{{1,522},{510,383}}</string>
                <key>offset</key>
                <string>{0,0}</string>
                <key>rotated</key>
                <false/>
                <key>sourceColorRect</key>
                <string>{{0,0},{510,383}}</string>
                <key>sourceSize</key>
                <string>{510,383}</string>
            </dict>
            <key>066_16BackNew.png</key>
            <dict>
                <key>frame</key>
                <string>{{511,522},{510,383}}</string>
                <key>offset</key>
                <string>{0,0}</string>
                <key>rotated</key>
                <false/>
                <key>sourceColorRect</key>
                <string>{{0,0},{510,383}}</string>
                <key>sourceSize</key>
                <string>{510,383}</string>
            </dict>
        </dict>
        <key>metadata</key>
        <dict>
            <key>format</key>
            <integer>2</integer>
            <key>realTextureFileName</key>
            <string>Synergy5.png</string>
            <key>size</key>
            <string>{1024,1024}</string>
            <key>smartupdate</key>
            <string>$TexturePacker:SmartUpdate:400c14f5a251117a2a9c98c536f58cd5$</string>
            <key>textureFileName</key>
            <string>Synergy5.png</string>
        </dict>
    </dict>

